emgio/__init__.py
emgio/version.py
emgio/analysis/__init__.py
emgio/analysis/signal.py
emgio/analysis/verification.py
emgio/core/__init__.py
emgio/core/emg.py
emgio/exporters/__init__.py
emgio/exporters/edf.py
emgio/importers/__init__.py
emgio/importers/base.py
emgio/importers/csv.py
emgio/importers/edf.py
emgio/importers/eeglab.py
emgio/importers/otb.py
emgio/importers/trigno.py
emgio/importers/wfdb.py
emgio/importers/xdf.py
emgio/tests/__init__.py
emgio/tests/test_core.py
emgio/tests/test_eeglab_importer.py
emgio/tests/test_exporters.py
emgio/tests/test_importer_wfdb.py
emgio/tests/test_importers.py
emgio/tests/test_verification.py
emgio/tests/test_visualization.py
emgio/tests/test_xdf_importer.py
emgio/utils/__init__.py
emgio/visualization/__init__.py
emgio/visualization/static.py
emgio-0.2.2.dist-info/licenses/LICENSE
emgio-0.2.2.dist-info/METADATA
emgio-0.2.2.dist-info/WHEEL
emgio-0.2.2.dist-info/top_level.txt
emgio-0.2.2.dist-info/RECORD
