Metadata-Version: 2.4
Name: emgio
Version: 0.2.2
Summary: A Python package for EMG data import/export and manipulation with unified interface for various EMG systems
Author-email: Seyed Yahya Shirazi <shirazi@ieee.org>
Maintainer-email: Seyed Yahya Shirazi <shirazi@ieee.org>
License: BSD 3-Clause License
Project-URL: Homepage, https://github.com/neuromechanist/emgio
Project-URL: Documentation, https://neuromechanist.github.io/emgio/
Project-URL: Repository, https://github.com/neuromechanist/emgio
Project-URL: Issues, https://github.com/neuromechanist/emgio/issues
Project-URL: Changelog, https://github.com/neuromechanist/emgio/releases
Keywords: emg,electromyography,biosignal,edf,bdf,wfdb,trigno,delsys,neuroscience,signal-processing
Classifier: Development Status :: 4 - Beta
Classifier: Intended Audience :: Science/Research
Classifier: Intended Audience :: Healthcare Industry
Classifier: License :: OSI Approved :: BSD License
Classifier: Operating System :: OS Independent
Classifier: Programming Language :: Python :: 3
Classifier: Programming Language :: Python :: 3.11
Classifier: Programming Language :: Python :: 3.12
Classifier: Programming Language :: Python :: 3.13
Classifier: Programming Language :: Python :: 3.14
Classifier: Topic :: Scientific/Engineering
Classifier: Topic :: Scientific/Engineering :: Bio-Informatics
Classifier: Topic :: Scientific/Engineering :: Medical Science Apps.
Requires-Python: >=3.11
License-File: LICENSE
Requires-Dist: numpy>=1.20.0
Requires-Dist: pandas>=1.3.0
Requires-Dist: scipy>=1.7.0
Requires-Dist: matplotlib>=3.4.0
Requires-Dist: pyedflib>=0.1.30
Requires-Dist: wfdb>=4.0.0
Requires-Dist: pyxdf>=1.16.0
Provides-Extra: dev
Requires-Dist: pytest>=7.0.0; extra == "dev"
Requires-Dist: pytest-cov>=4.0.0; extra == "dev"
Requires-Dist: ruff>=0.1.0; extra == "dev"
Provides-Extra: docs
Requires-Dist: mkdocs>=1.6.0; extra == "docs"
Requires-Dist: mkdocs-material>=9.5.0; extra == "docs"
Requires-Dist: mkdocstrings[python]>=1.0.0; extra == "docs"
Requires-Dist: pymdown-extensions>=10.10.0; extra == "docs"
Requires-Dist: mkdocs-jupyter>=0.25.0; extra == "docs"
Requires-Dist: mike>=2.1.0; extra == "docs"
Provides-Extra: all
Requires-Dist: emgio[dev,docs]; extra == "all"
Dynamic: license-file
